eve/__init__.py
eve/__main__.py
eve/app.py
eve/code.py
eve/error.py
eve/file.py
eve/grammar.py
eve/lex.py
eve/syntax.py
eve/token.py
eve/translation.py
eve/trees.py
eve/types.py
eve/utils.py
eve/zones.py
eve/embedding/__init__.py
eve/embedding/nqs.py
eve/embedding/python.py
eve/templates/__init__.py
eve/templates/english.py
eve/templates/french.py
eve/templates/spanish.py
nateve_eve-0.0.1a1.dist-info/LICENSE
nateve_eve-0.0.1a1.dist-info/METADATA
nateve_eve-0.0.1a1.dist-info/WHEEL
nateve_eve-0.0.1a1.dist-info/entry_points.txt
nateve_eve-0.0.1a1.dist-info/top_level.txt
nateve_eve-0.0.1a1.dist-info/RECORD
