Metadata-Version: 2.1
Name: nateve-eve
Version: 0.0.1a1
Summary: Nateve tokenizer developed with python 3.8
Home-page: https://github.com/NateveLang/Eve
Author: Emmanuel Norambuena
Author-email: eanorambuena@uc.cl
License: MIT
Download-URL: https://github.com/NateveLang/Eve/archive/v0.0.1a1.tar.gz
Project-URL: Bug Reports, https://github.com/NateveLang/Eve/issues
Project-URL: Source, https://github.com/NateveLang/Eve
Keywords: development,quantum computing,programming language,nateve,natevelang,nate,education
Platform: UNKNOWN
Classifier: Development Status :: 3 - Alpha
Classifier: Intended Audience :: Developers
Classifier: Topic :: Software Development :: Build Tools
Classifier: License :: OSI Approved :: MIT License
Classifier: Programming Language :: Python :: 3
Classifier: Programming Language :: Python :: 3.5
Classifier: Programming Language :: Python :: 3.6
Classifier: Programming Language :: Python :: 3.7
Classifier: Programming Language :: Python :: 3.8
Requires-Python: >=3.5, <=3.8
License-File: LICENSE
Requires-Dist: eggdriver
